{
  "endpointAddress" : "https://api.randomuser.me/",
  "method" : "GET",
  "headers" : { },
  "redirectEnabled" : true,
  "requestBody" : "",
  "queryParams" : {
    "results" : "15"
  },
  "authDetails" : null,
  "contentType" : "application/json",
  "multiParamInfoList" : null,
  "sampleHttpResponseDetails" : {
    "statusCode" : 0,
    "headers" : {
      "content-type" : [ "application/json; charset=utf-8" ],
      "cache-control" : [ "no-cache" ]
    },
    "responseBody" : "{\"results\":[{\"gender\":\"female\",\"name\":{\"title\":\"miss\",\"first\":\"sofie\",\"last\":\"rasmussen\"},\"location\":{\"street\":\"9541 skolegade\",\"city\":\"brondby\",\"state\":\"sjælland\",\"postcode\":15916,\"coordinates\":{\"latitude\":\"-27.3883\",\"longitude\":\"61.6873\"},\"timezone\":{\"offset\":\"-6:00\",\"description\":\"Central Time (US & Canada), Mexico City\"}},\"email\":\"sofie.rasmussen@example.com\",\"login\":{\"uuid\":\"ee43fb2c-18eb-43ff-a400-370708adf63e\",\"username\":\"angryelephant510\",\"password\":\"aaaaaa\",\"salt\":\"G7Rm89yr\",\"md5\":\"228590078f28d5628864d9a8afe4fb09\",\"sha1\":\"934e7340c254713b8c75e461d5ee51d829ce3a68\",\"sha256\":\"976a37ed43c7cfd79f6f07e2be1dd69982ddcedd19c53412367b3e6965304e7b\"},\"dob\":{\"date\":\"1945-07-05T07:25:37Z\",\"age\":73},\"registered\":{\"date\":\"2009-10-19T09:13:59Z\",\"age\":9},\"phone\":\"56894193\",\"cell\":\"83472811\",\"id\":{\"name\":\"CPR\",\"value\":\"887423-7837\"},\"picture\":{\"large\":\"https://randomuser.me/api/portraits/women/3.jpg\",\"medium\":\"https://randomuser.me/api/portraits/med/women/3.jpg\",\"thumbnail\":\"https://randomuser.me/api/portraits/thumb/women/3.jpg\"},\"nat\":\"DK\"},{\"gender\":\"male\",\"name\":{\"title\":\"mr\",\"first\":\"lias\",\"last\":\"helgøy\"},\"location\":{\"street\":\"åslandhellinga 7358\",\"city\":\"sveio\",\"state\":\"oslo\",\"postcode\":\"0363\",\"coordinates\":{\"latitude\":\"-22.1391\",\"longitude\":\"116.8085\"},\"timezone\":{\"offset\":\"+5:30\",\"description\":\"Bombay, Calcutta, Madras, New Delhi\"}},\"email\":\"lias.helgøy@example.com\",\"login\":{\"uuid\":\"56c4d21e-db64-44ce-9bc3-85b5fc9a1121\",\"username\":\"bluezebra787\",\"password\":\"hello1\",\"salt\":\"efigvBaL\",\"md5\":\"3f2ab8c9daa1f9da4449b72305f6a7d8\",\"sha1\":\"b711f129acc45b62b4d4d9871630cd4dc16c22d1\",\"sha256\":\"2c9a877b235dada854cd1aa96b531095502a4d403da9a44e56c1b98a66f3e3f0\"},\"dob\":{\"date\":\"1977-01-14T22:20:22Z\",\"age\":42},\"registered\":{\"date\":\"2011-02-20T16:01:27Z\",\"age\":8},\"phone\":\"64521708\",\"cell\":\"95518666\",\"id\":{\"name\":\"FN\",\"value\":\"14017740254\"},\"picture\":{\"large\":\"https://randomuser.me/api/portraits/men/48.jpg\",\"medium\":\"https://randomuser.me/api/portraits/med/men/48.jpg\",\"thumbnail\":\"https://randomuser.me/api/portraits/thumb/men/48.jpg\"},\"nat\":\"NO\"},{\"gender\":\"male\",\"name\":{\"title\":\"mr\",\"first\":\"kenan\",\"last\":\"akyürek\"},\"location\":{\"street\":\"5212 maçka cd\",\"city\":\"niğde\",\"state\":\"sivas\",\"postcode\":51805,\"coordinates\":{\"latitude\":\"-27.8581\",\"longitude\":\"-18.1146\"},\"timezone\":{\"offset\":\"+5:30\",\"description\":\"Bombay, Calcutta, Madras, New Delhi\"}},\"email\":\"kenan.akyürek@example.com\",\"login\":{\"uuid\":\"0962fc98-7879-442b-8dd8-82d99a3b0e68\",\"username\":\"purpleleopard950\",\"password\":\"gambler\",\"salt\":\"v0DOgJHz\",\"md5\":\"aef2eff59bc9be9962ad862b4e41a9de\",\"sha1\":\"9376eb77f67d405f4c317da76a601005fd87dfc8\",\"sha256\":\"fc009a23e3762ee6f5993a6b700d38671c8760d517453cc04c9adfe9d06cd2c7\"},\"dob\":{\"date\":\"1987-10-03T15:58:04Z\",\"age\":31},\"registered\":{\"date\":\"2009-11-27T21:45:58Z\",\"age\":9},\"phone\":\"(606)-047-8817\",\"cell\":\"(978)-312-3117\",\"id\":{\"name\":\"\",\"value\":null},\"picture\":{\"large\":\"https://randomuser.me/api/portraits/men/89.jpg\",\"medium\":\"https://randomuser.me/api/portraits/med/men/89.jpg\",\"thumbnail\":\"https://randomuser.me/api/portraits/thumb/men/89.jpg\"},\"nat\":\"TR\"},{\"gender\":\"male\",\"name\":{\"title\":\"mr\",\"first\":\"grayson\",\"last\":\"walker\"},\"location\":{\"street\":\"3496 tay street\",\"city\":\"blenheim\",\"state\":\"southland\",\"postcode\":85937,\"coordinates\":{\"latitude\":\"-75.1295\",\"longitude\":\"73.4828\"},\"timezone\":{\"offset\":\"-1:00\",\"description\":\"Azores, Cape Verde Islands\"}},\"email\":\"grayson.walker@example.com\",\"login\":{\"uuid\":\"8bab75f7-a198-466a-8fd7-e90a17cde3be\",\"username\":\"sadbear132\",\"password\":\"volley\",\"salt\":\"ta3oa69K\",\"md5\":\"733654d77757dbd945b4674555eafb7e\",\"sha1\":\"2a1a78e65af448a877859bff853e55f7bdf4a548\",\"sha256\":\"08a82c8ce5f1f8b6e5156f71487bf7888fa3a338993f55547774cc7e3ef1bfeb\"},\"dob\":{\"date\":\"1948-08-09T19:42:34Z\",\"age\":70},\"registered\":{\"date\":\"2013-06-07T03:48:40Z\",\"age\":5},\"phone\":\"(318)-245-2156\",\"cell\":\"(793)-862-1682\",\"id\":{\"name\":\"\",\"value\":null},\"picture\":{\"large\":\"https://randomuser.me/api/portraits/men/91.jpg\",\"medium\":\"https://randomuser.me/api/portraits/med/men/91.jpg\",\"thumbnail\":\"https://randomuser.me/api/portraits/thumb/men/91.jpg\"},\"nat\":\"NZ\"},{\"gender\":\"female\",\"name\":{\"title\":\"ms\",\"first\":\"پرنیا\",\"last\":\"علیزاده\"},\"location\":{\"street\":\"5229 آذربایجان\",\"city\":\"ملارد\",\"state\":\"یزد\",\"postcode\":85555,\"coordinates\":{\"latitude\":\"46.6511\",\"longitude\":\"137.7450\"},\"timezone\":{\"offset\":\"-9:00\",\"description\":\"Alaska\"}},\"email\":\"پرنیا.علیزاده@example.com\",\"login\":{\"uuid\":\"613522cd-36c6-45d1-ad40-e30ef9fb001b\",\"username\":\"yellowrabbit208\",\"password\":\"112233\",\"salt\":\"Tk1H6Jem\",\"md5\":\"6e5a18b9dd10b5e60bafc35ac98d6144\",\"sha1\":\"4a80422be62e34b626d225e7ece3d7f2946aa771\",\"sha256\":\"0324d0836c47ed44930c9d18468c3283b5b47d935e7c019e9aee2ef29c2f5ee8\"},\"dob\":{\"date\":\"1983-08-06T07:05:25Z\",\"age\":35},\"registered\":{\"date\":\"2011-10-13T09:27:27Z\",\"age\":7},\"phone\":\"010-02035692\",\"cell\":\"0918-333-1018\",\"id\":{\"name\":\"\",\"value\":null},\"picture\":{\"large\":\"https://randomuser.me/api/portraits/women/12.jpg\",\"medium\":\"https://randomuser.me/api/portraits/med/women/12.jpg\",\"thumbnail\":\"https://randomuser.me/api/portraits/thumb/women/12.jpg\"},\"nat\":\"IR\"},{\"gender\":\"female\",\"name\":{\"title\":\"miss\",\"first\":\"ava\",\"last\":\"bouchard\"},\"location\":{\"street\":\"9069 grand marais ave\",\"city\":\"cumberland\",\"state\":\"new brunswick\",\"postcode\":\"J6T 6M5\",\"coordinates\":{\"latitude\":\"73.8942\",\"longitude\":\"-51.0355\"},\"timezone\":{\"offset\":\"+5:45\",\"description\":\"Kathmandu\"}},\"email\":\"ava.bouchard@example.com\",\"login\":{\"uuid\":\"2d369328-abe5-4da3-aad4-bad7d180bfdb\",\"username\":\"heavydog845\",\"password\":\"4040\",\"salt\":\"Vw2ia8sB\",\"md5\":\"16e8d8f88f88f05dbd917bf22d7f7889\",\"sha1\":\"f208bd4df2c6c89b20287ce13d39e69b1fc9800a\",\"sha256\":\"88721b12e56ae435068017474dea3a5886389a888e769fbcd00abb7b684e98ff\"},\"dob\":{\"date\":\"1967-02-10T07:12:47Z\",\"age\":52},\"registered\":{\"date\":\"2004-12-06T04:02:52Z\",\"age\":14},\"phone\":\"528-549-9344\",\"cell\":\"424-548-6901\",\"id\":{\"name\":\"\",\"value\":null},\"picture\":{\"large\":\"https://randomuser.me/api/portraits/women/92.jpg\",\"medium\":\"https://randomuser.me/api/portraits/med/women/92.jpg\",\"thumbnail\":\"https://randomuser.me/api/portraits/thumb/women/92.jpg\"},\"nat\":\"CA\"},{\"gender\":\"female\",\"name\":{\"title\":\"mrs\",\"first\":\"هلیا\",\"last\":\"کامروا\"},\"location\":{\"street\":\"6343 میدان دکتر فاطمی / جهاد\",\"city\":\"سبزوار\",\"state\":\"قم\",\"postcode\":81717,\"coordinates\":{\"latitude\":\"-59.8270\",\"longitude\":\"127.1391\"},\"timezone\":{\"offset\":\"+1:00\",\"description\":\"Brussels, Copenhagen, Madrid, Paris\"}},\"email\":\"هلیا.کامروا@example.com\",\"login\":{\"uuid\":\"8e9130fc-1b92-4201-8069-ae42d655202c\",\"username\":\"bigrabbit117\",\"password\":\"lkjh\",\"salt\":\"Z26LX0LH\",\"md5\":\"b74992a94673e06a65189d48b3a0b496\",\"sha1\":\"b2258312b19295ed99d370298aaef45bad7ab3a9\",\"sha256\":\"2c3478d691ce03c56b9d62173f3c1ede534e9e0b339e6e82d11e10bc49bc025a\"},\"dob\":{\"date\":\"1978-12-15T22:13:13Z\",\"age\":40},\"registered\":{\"date\":\"2003-03-11T09:26:03Z\",\"age\":15},\"phone\":\"006-31089666\",\"cell\":\"0986-669-9275\",\"id\":{\"name\":\"\",\"value\":null},\"picture\":{\"large\":\"https://randomuser.me/api/portraits/women/48.jpg\",\"medium\":\"https://randomuser.me/api/portraits/med/women/48.jpg\",\"thumbnail\":\"https://randomuser.me/api/portraits/thumb/women/48.jpg\"},\"nat\":\"IR\"},{\"gender\":\"female\",\"name\":{\"title\":\"miss\",\"first\":\"falviana\",\"last\":\"aragão\"},\"location\":{\"street\":\"9601 rua paraná \",\"city\":\"petrolina\",\"state\":\"paraíba\",\"postcode\":55275,\"coordinates\":{\"latitude\":\"-65.5471\",\"longitude\":\"35.0362\"},\"timezone\":{\"offset\":\"+1:00\",\"description\":\"Brussels, Copenhagen, Madrid, Paris\"}},\"email\":\"falviana.aragão@example.com\",\"login\":{\"uuid\":\"213ce833-7c5d-420f-8707-2d62f93d87fe\",\"username\":\"organicdog125\",\"password\":\"omega1\",\"salt\":\"O0h8NMxg\",\"md5\":\"75b1e38b5b895dc063ce5d9af4150892\",\"sha1\":\"b62b381cfa2e53a269ed8a648738fc39930f50c3\",\"sha256\":\"f76f02aa04e793c432069461209b170caadb65b82c85e0b9bf297fed08a9d916\"},\"dob\":{\"date\":\"1974-03-09T10:39:43Z\",\"age\":44},\"registered\":{\"date\":\"2005-05-04T22:08:46Z\",\"age\":13},\"phone\":\"(69) 8760-2514\",\"cell\":\"(63) 5736-7895\",\"id\":{\"name\":\"\",\"value\":null},\"picture\":{\"large\":\"https://randomuser.me/api/portraits/women/72.jpg\",\"medium\":\"https://randomuser.me/api/portraits/med/women/72.jpg\",\"thumbnail\":\"https://randomuser.me/api/portraits/thumb/women/72.jpg\"},\"nat\":\"BR\"},{\"gender\":\"female\",\"name\":{\"title\":\"miss\",\"first\":\"meral\",\"last\":\"bolatlı\"},\"location\":{\"street\":\"7183 kushimoto sk\",\"city\":\"şırnak\",\"state\":\"bolu\",\"postcode\":34601,\"coordinates\":{\"latitude\":\"-31.5740\",\"longitude\":\"-33.6991\"},\"timezone\":{\"offset\":\"+2:00\",\"description\":\"Kaliningrad, South Africa\"}},\"email\":\"meral.bolatlı@example.com\",\"login\":{\"uuid\":\"764797ea-f025-4aca-b9ba-cd57ab89cdde\",\"username\":\"ticklishsnake560\",\"password\":\"sandy1\",\"salt\":\"VDm9SsMo\",\"md5\":\"bfdeb5e7070ebeb6d5ea6a889d115804\",\"sha1\":\"85d6440f5701a1af03a31183f585c14a86dbb90b\",\"sha256\":\"e216eb235bf4731a840751d950a0071d3888b01a51db41f9a18c31046f13c763\"},\"dob\":{\"date\":\"1996-01-15T19:25:20Z\",\"age\":23},\"registered\":{\"date\":\"2004-02-06T17:09:54Z\",\"age\":15},\"phone\":\"(770)-193-8956\",\"cell\":\"(397)-794-8582\",\"id\":{\"name\":\"\",\"value\":null},\"picture\":{\"large\":\"https://randomuser.me/api/portraits/women/83.jpg\",\"medium\":\"https://randomuser.me/api/portraits/med/women/83.jpg\",\"thumbnail\":\"https://randomuser.me/api/portraits/thumb/women/83.jpg\"},\"nat\":\"TR\"},{\"gender\":\"female\",\"name\":{\"title\":\"ms\",\"first\":\"etta\",\"last\":\"rauch\"},\"location\":{\"street\":\"meisenweg 88\",\"city\":\"vacha\",\"state\":\"berlin\",\"postcode\":70822,\"coordinates\":{\"latitude\":\"17.9512\",\"longitude\":\"104.6235\"},\"timezone\":{\"offset\":\"0:00\",\"description\":\"Western Europe Time, London, Lisbon, Casablanca\"}},\"email\":\"etta.rauch@example.com\",\"login\":{\"uuid\":\"f9881c0a-070a-4520-9fbb-aeaabff4b91c\",\"username\":\"bluesnake405\",\"password\":\"goodbye\",\"salt\":\"VXWcF02X\",\"md5\":\"8ab4944da168edeadca90abb6a37294e\",\"sha1\":\"435448a24eafd8615ad76bc71d1ea646000a1ccb\",\"sha256\":\"02a38daeb49dbf8964eba99744fb471b524c2207ea9a44c0f1d280500c4d1e00\"},\"dob\":{\"date\":\"1949-12-26T20:46:24Z\",\"age\":69},\"registered\":{\"date\":\"2018-04-16T06:35:22Z\",\"age\":0},\"phone\":\"0853-3157243\",\"cell\":\"0179-3987767\",\"id\":{\"name\":\"\",\"value\":null},\"picture\":{\"large\":\"https://randomuser.me/api/portraits/women/18.jpg\",\"medium\":\"https://randomuser.me/api/portraits/med/women/18.jpg\",\"thumbnail\":\"https://randomuser.me/api/portraits/thumb/women/18.jpg\"},\"nat\":\"DE\"},{\"gender\":\"male\",\"name\":{\"title\":\"mr\",\"first\":\"ivan\",\"last\":\"castillo\"},\"location\":{\"street\":\"3602 paseo de zorrilla\",\"city\":\"guadalajara\",\"state\":\"región de murcia\",\"postcode\":78820,\"coordinates\":{\"latitude\":\"-31.4231\",\"longitude\":\"-168.1907\"},\"timezone\":{\"offset\":\"+3:30\",\"description\":\"Tehran\"}},\"email\":\"ivan.castillo@example.com\",\"login\":{\"uuid\":\"27f7a88a-f1fa-4961-a920-83b9ecca1482\",\"username\":\"redsnake879\",\"password\":\"lucas1\",\"salt\":\"sIh5LzKn\",\"md5\":\"f1ae8a0d1585a8c6b303d3b8041f8d63\",\"sha1\":\"6e6f03fc4a25f5c1f303dca489467a5482c15a24\",\"sha256\":\"848751f6094eb1d3181f6c659b4354586de9099f99957debcaeb89274b3a7f09\"},\"dob\":{\"date\":\"1995-11-19T08:33:35Z\",\"age\":23},\"registered\":{\"date\":\"2002-05-08T20:57:18Z\",\"age\":16},\"phone\":\"931-075-676\",\"cell\":\"613-338-644\",\"id\":{\"name\":\"DNI\",\"value\":\"32083870-Q\"},\"picture\":{\"large\":\"https://randomuser.me/api/portraits/men/25.jpg\",\"medium\":\"https://randomuser.me/api/portraits/med/men/25.jpg\",\"thumbnail\":\"https://randomuser.me/api/portraits/thumb/men/25.jpg\"},\"nat\":\"ES\"},{\"gender\":\"male\",\"name\":{\"title\":\"mr\",\"first\":\"jesse\",\"last\":\"moreno\"},\"location\":{\"street\":\"732 w sherman dr\",\"city\":\"bundaberg\",\"state\":\"australian capital territory\",\"postcode\":2341,\"coordinates\":{\"latitude\":\"-9.5990\",\"longitude\":\"49.6604\"},\"timezone\":{\"offset\":\"-6:00\",\"description\":\"Central Time (US & Canada), Mexico City\"}},\"email\":\"jesse.moreno@example.com\",\"login\":{\"uuid\":\"59b5abde-8eaa-4308-b3e2-4c73fb493cdd\",\"username\":\"greenswan662\",\"password\":\"sheep\",\"salt\":\"zA03oQHO\",\"md5\":\"87a4bfda67d6e7c7939673253750d029\",\"sha1\":\"ecb0326db561faa1ef0979165b15afb86f4fd97f\",\"sha256\":\"188245597f39dcd06cf8bef6d96e15d778aee9eb83f30a37a3d33887b51965b7\"},\"dob\":{\"date\":\"1973-11-25T14:25:22Z\",\"age\":45},\"registered\":{\"date\":\"2008-04-13T17:20:49Z\",\"age\":10},\"phone\":\"02-9476-0416\",\"cell\":\"0409-877-842\",\"id\":{\"name\":\"TFN\",\"value\":\"878350730\"},\"picture\":{\"large\":\"https://randomuser.me/api/portraits/men/27.jpg\",\"medium\":\"https://randomuser.me/api/portraits/med/men/27.jpg\",\"thumbnail\":\"https://randomuser.me/api/portraits/thumb/men/27.jpg\"},\"nat\":\"AU\"},{\"gender\":\"male\",\"name\":{\"title\":\"mr\",\"first\":\"miguel\",\"last\":\"caballero\"},\"location\":{\"street\":\"181 calle covadonga\",\"city\":\"móstoles\",\"state\":\"navarra\",\"postcode\":27834,\"coordinates\":{\"latitude\":\"2.1450\",\"longitude\":\"170.2258\"},\"timezone\":{\"offset\":\"+11:00\",\"description\":\"Magadan, Solomon Islands, New Caledonia\"}},\"email\":\"miguel.caballero@example.com\",\"login\":{\"uuid\":\"1dcc02e5-df8b-44fb-8f7c-9d44d4ab7bae\",\"username\":\"goldenwolf251\",\"password\":\"mariposa\",\"salt\":\"nOaXtjAf\",\"md5\":\"fcdf0e47a16d960c6cdc650dfdc711d0\",\"sha1\":\"02fd6eed2a3061f5b8484393cad08049d3d00fd0\",\"sha256\":\"5383ebb0527fb8795540d160b4c3ec029e01ffd7310e717a40782e9ba2cdd600\"},\"dob\":{\"date\":\"1956-09-04T02:24:12Z\",\"age\":62},\"registered\":{\"date\":\"2017-05-10T11:58:07Z\",\"age\":1},\"phone\":\"997-050-089\",\"cell\":\"693-804-608\",\"id\":{\"name\":\"DNI\",\"value\":\"92781697-V\"},\"picture\":{\"large\":\"https://randomuser.me/api/portraits/men/59.jpg\",\"medium\":\"https://randomuser.me/api/portraits/med/men/59.jpg\",\"thumbnail\":\"https://randomuser.me/api/portraits/thumb/men/59.jpg\"},\"nat\":\"ES\"},{\"gender\":\"male\",\"name\":{\"title\":\"mr\",\"first\":\"alessio\",\"last\":\"muller\"},\"location\":{\"street\":\"3466 rue chazière\",\"city\":\"saint-étienne\",\"state\":\"cantal\",\"postcode\":76899,\"coordinates\":{\"latitude\":\"-66.7585\",\"longitude\":\"63.2894\"},\"timezone\":{\"offset\":\"-1:00\",\"description\":\"Azores, Cape Verde Islands\"}},\"email\":\"alessio.muller@example.com\",\"login\":{\"uuid\":\"ccc08fdc-62d5-41f3-a855-18c475e6fecc\",\"username\":\"greendog381\",\"password\":\"marma\",\"salt\":\"irqLAnL8\",\"md5\":\"c9f4362faa6e673a3f3e1045c5c6da0a\",\"sha1\":\"760038336b84146067d8a5f67851bfad204efe79\",\"sha256\":\"239214347ca5dd09f0f8794313a8046545a353de97415803691933b15cbb8a52\"},\"dob\":{\"date\":\"1951-10-23T02:58:20Z\",\"age\":67},\"registered\":{\"date\":\"2016-05-04T04:47:34Z\",\"age\":2},\"phone\":\"05-36-78-09-20\",\"cell\":\"06-38-73-20-33\",\"id\":{\"name\":\"INSEE\",\"value\":\"1NNaN06769036 65\"},\"picture\":{\"large\":\"https://randomuser.me/api/portraits/men/1.jpg\",\"medium\":\"https://randomuser.me/api/portraits/med/men/1.jpg\",\"thumbnail\":\"https://randomuser.me/api/portraits/thumb/men/1.jpg\"},\"nat\":\"FR\"},{\"gender\":\"male\",\"name\":{\"title\":\"mr\",\"first\":\"scott\",\"last\":\"parker\"},\"location\":{\"street\":\"3080 dane st\",\"city\":\"geelong\",\"state\":\"victoria\",\"postcode\":4697,\"coordinates\":{\"latitude\":\"21.0996\",\"longitude\":\"105.1236\"},\"timezone\":{\"offset\":\"+5:45\",\"description\":\"Kathmandu\"}},\"email\":\"scott.parker@example.com\",\"login\":{\"uuid\":\"7538295f-5fc4-481e-9693-8addf04620b9\",\"username\":\"greenlion473\",\"password\":\"penguin1\",\"salt\":\"1nQSjtPG\",\"md5\":\"7e68f62dadd11a075f336733928900b2\",\"sha1\":\"f0b7f5e8fb143e5e47d718e607e5e430799bdfd6\",\"sha256\":\"1bd705e78c7cdacab4c51a130c95cd5cd2f1adb785436dba378baeae9f48d1d8\"},\"dob\":{\"date\":\"1963-10-29T13:55:14Z\",\"age\":55},\"registered\":{\"date\":\"2017-07-21T15:00:02Z\",\"age\":1},\"phone\":\"04-1495-4391\",\"cell\":\"0455-217-666\",\"id\":{\"name\":\"TFN\",\"value\":\"869990760\"},\"picture\":{\"large\":\"https://randomuser.me/api/portraits/men/1.jpg\",\"medium\":\"https://randomuser.me/api/portraits/med/men/1.jpg\",\"thumbnail\":\"https://randomuser.me/api/portraits/thumb/men/1.jpg\"},\"nat\":\"AU\"}],\"info\":{\"seed\":\"cca6bd047aeaa816\",\"results\":15,\"page\":1,\"version\":\"1.2\"}}",
    "convertedResponse" : null
  }
}